applitools/__init__.py
applitools/eyes_universal/__init__.py
applitools/eyes_universal/__main__.py
applitools/eyes_universal/instance.py
applitools/eyes_universal/server.py
applitools/eyes_universal/bin/eyes-universal
eyes_universal-4.0.1.dist-info/LICENSE
eyes_universal-4.0.1.dist-info/METADATA
eyes_universal-4.0.1.dist-info/WHEEL
eyes_universal-4.0.1.dist-info/top_level.txt
eyes_universal-4.0.1.dist-info/RECORD
